{
  "shop_id": "SHOP_92CC95195D",
  "shop_name": "Align & Smile Dental Care- Multi-speciality Dental Clinic",
  "category": "dentist",
  "city": "Noida",
  "country": "india",
  "address": "First Floor, J 45, near Swagath restaurant, J Block, Pocket L, Sector 18, Noida, Uttar Pradesh 201301",
  "phone": "083689 12550",
  "email": "",
  "instagram": "",
  "facebook": "",
  "twitter": "",
  "linkedin": "",
  "google_maps_url": "https://www.google.com/maps/place/Dentique+Dental+%26+Implant+Centre/@28.5712294,77.3103934,13z/data=!4m11!1m3!2m2!1sdentist+in+Noida!6e1!3m6!1s0x390cef60600216f5:0x7b14afb0c695c23b!8m2!3d28.5712294!4d77.3824912!15sChBkZW50aXN0IGluIE5vaWRhWhIiEGRlbnRpc3QgaW4gbm9pZGGSAQ1kZW50YWxfY2xpbmlj4AEA!16s%2Fg%2F11f3xzn2pl?entry=ttu&g_ep=EgoyMDI2MDQyMi4wIKXMDSoASAFQAw%3D%3D",
  "rating": 4.9,
  "reviews_count": 199,
  "website_url": "http://www.alignsmilenoida.com/",
  "deployed_url": "",
  "generated_website": "",
  "preview_path": "india/noida/dentist/0x390cef60600216f5-0x7b14afb0c695c23b",
  "build_status": "error",
  "review_status": "rejected",
  "review_notes": "Missing VERCEL_TOKEN",
  "generated_at": "2026-04-27T11:15:59.062Z",
  "review_updated_at": "2026-04-27T11:15:59.071Z"
}
