{
  "shop_id": "SHOP_E6B9576D04",
  "shop_name": "The Perfect 32 Dental Clinic (Dr Madhur Navlani & Dr Srishti Navlani)",
  "category": "dentist",
  "city": "indore",
  "country": "india",
  "address": "103, K. K. Bapna Arcade, 7/1 Race Course Road, Zanjeerwala Square, Indore, Madhya Pradesh 452003",
  "phone": "086022 38440",
  "email": "",
  "instagram": "https://instagram.com/deepalidentalclinic",
  "facebook": "https://m.facebook.com/drdevperfectsmiledentalclinic",
  "twitter": "https://book.healthplix.com/dr-pinak-bhatnagar-indore-indore",
  "linkedin": "",
  "google_maps_url": "https://www.google.com/maps/place/The+Perfect+32+Dental+Clinic+(Dr+Madhur+Navlani+%26+Dr+Srishti+Navlani)/@22.7195594,75.8094814,13z/data=!4m10!1m2!2m1!1sdentist+in+indore!3m6!1s0x3962fd40a144a8cd:0xab3d2da741a9b17c!8m2!3d22.7258703!4d75.8812396!15sChFkZW50aXN0IGluIGluZG9yZVoTIhFkZW50aXN0IGluIGluZG9yZZIBDWRlbnRhbF9jbGluaWPgAQA!16s%2Fg%2F1tdncnh_?entry=ttu&g_ep=EgoyMDI2MDQyMi4wIKXMDSoASAFQAw%3D%3D",
  "rating": 4.9,
  "reviews_count": 151,
  "website_url": "http://www.theperfect32.com/",
  "deployed_url": "",
  "generated_website": "",
  "preview_path": "india/indore/dentist/0x3962fd40a144a8cd-0xab3d2da741a9b17c",
  "build_status": "error",
  "review_status": "good",
  "review_notes": "",
  "generated_at": "2026-04-27T15:10:32.407Z",
  "review_updated_at": "2026-05-02T15:35:12Z",
  "status": "good",
  "reason": "",
  "local_file_url": "file:///P:/Creative-client-/Leads/backend/output/india/indore/dentist/0x3962fd40a144a8cd-0xab3d2da741a9b17c/index.html"
}
